yacrawler/__init__.py
yacrawler/__main__.py
yacrawler/run.py
yacrawler/cli/__init__.py
yacrawler/cli/cli.py
yacrawler/cli/cli_logger.py
yacrawler/core/__init__.py
yacrawler/core/adapter.py
yacrawler/core/engine.py
yacrawler/core/pipeline.py
yacrawler/core/request.py
yacrawler/core/response.py
yacrawler/tui/__init__.py
yacrawler/tui/tui.py
yacrawler/tui/tui_logger.py
yacrawler/utilities/__init__.py
yacrawler/utilities/aioadapter.py
yacrawler/utilities/discoverers.py
yacrawler/utilities/processors.py
yacrawler-0.1.3.dist-info/licenses/LICENSE
yacrawler-0.1.3.dist-info/METADATA
yacrawler-0.1.3.dist-info/WHEEL
yacrawler-0.1.3.dist-info/top_level.txt
yacrawler-0.1.3.dist-info/RECORD
