Metadata-Version: 2.4
Name: yacrawler
Version: 0.1.3
Summary: Yet Another Internet Carwler
Requires-Python: >=3.10
License-File: LICENSE
Requires-Dist: asyncio>=3.4.3
Provides-Extra: tui
Requires-Dist: textual>=3.2.0; extra == "tui"
Provides-Extra: cli
Requires-Dist: rich>=14.0.0; extra == "cli"
Provides-Extra: run
Requires-Dist: typer>=0.15.3; extra == "run"
Requires-Dist: click==8.1.8; extra == "run"
Provides-Extra: untilities
Requires-Dist: aiofiles>=24.1.0; extra == "untilities"
Requires-Dist: aiohttp>=3.11.18; extra == "untilities"
Provides-Extra: all
Requires-Dist: aiofiles>=24.1.0; extra == "all"
Requires-Dist: aiohttp>=3.11.18; extra == "all"
Requires-Dist: asyncio>=3.4.3; extra == "all"
Requires-Dist: rich>=14.0.0; extra == "all"
Requires-Dist: textual>=3.2.0; extra == "all"
Requires-Dist: typer>=0.15.3; extra == "all"
Requires-Dist: click==8.1.8; extra == "all"
Dynamic: license-file
